lektor_htmlmin.py
lektor_htmlmin-1.0.2.dist-info/DESCRIPTION.rst
lektor_htmlmin-1.0.2.dist-info/METADATA
lektor_htmlmin-1.0.2.dist-info/RECORD
lektor_htmlmin-1.0.2.dist-info/WHEEL
lektor_htmlmin-1.0.2.dist-info/entry_points.txt
lektor_htmlmin-1.0.2.dist-info/metadata.json
lektor_htmlmin-1.0.2.dist-info/top_level.txt
