Metadata-Version: 2.0
Name: lektor-htmlmin
Version: 1.0.2
Summary: HTML minifier for Lektor. Based on htmlmin.
Home-page: https://github.com/vesuvium/lektor-htmlmin
Author: Jacopo Cascioli
Author-email: jacopocascioli@gmail.com
License: MIT
Platform: UNKNOWN
Classifier: Environment :: Web Environment
Classifier: Operating System :: OS Independent
Classifier: Programming Language :: Python
Requires-Dist: htmlmin
Requires-Dist: chardet
